{
  "fetchedAt": "2026-07-08T14:10:31.810Z",
  "date": "2026/07/08",
  "news": [
    {
      "title": "數發部推AI算力中心",
      "summary": "數位發展部啟動首件數位促參案，推動AI算力中心建設，兩家業者通過資格審查。此舉將引導民間資金投入，強化台灣AI基礎設施，提升數位競爭力。",
      "region": "tw",
      "topic": "ai"
    },
    {
      "title": "台灣AI供應鏈迎變現期",
      "summary": "隨著代理式AI浪潮，台灣半導體供應鏈迎來獲利擴張期。路博邁點名處理器、記憶體、先進封裝等五大關鍵技術需求爆發，鞏固台灣在全球AI革命中心地位。",
      "region": "tw",
      "topic": "ai"
    },
    {
      "title": "台灣獵戶座衛星七月啟用",
      "summary": "台灣首顆自製衛星「獵戶座」（奇柏林）預計七月全面啟用，將應用於國安、環保、農業及防災。此為福爾摩沙衛星八號計畫首星，強化台灣太空產業實力。",
      "region": "tw",
      "topic": "sat"
    },
    {
      "title": "台灣大推海事衛星服務",
      "summary": "台灣大哥大攜手相宇集團及遠東醫電，整合高、中、低軌衛星，打造一站式海事衛星通訊方案。強化遠海通訊韌性，並延伸無人載具AI任務應用。",
      "region": "tw",
      "topic": "sat"
    },
    {
      "title": "遠傳引進亞馬遜Leo衛星",
      "summary": "遠傳電信與亞馬遜Leo簽署合作協議，成為台灣代理商，預計2027上半年啟動低軌衛星服務。此舉將強化台灣通訊基礎設施韌性，擴展服務範圍。",
      "region": "tw",
      "topic": "sat"
    },
    {
      "title": "美AI資料中心用電創新高",
      "summary": "美國能源情報署預測，受AI資料中心電力需求激增影響，美國今明兩年用電量將再創新高。商業用電量預計首次超越住宅用電，凸顯AI對能源的巨大需求。",
      "region": "int",
      "topic": "ai"
    },
    {
      "title": "歐盟推AI網路安全計畫",
      "summary": "歐盟委員會提出新計畫，應對先進AI在網路安全領域的風險與機遇。旨在加強數位環境安全，並建立AI模型評估能力，確保技術負責任發展。",
      "region": "int",
      "topic": "ai"
    },
    {
      "title": "中國擬限AI模型海外使用",
      "summary": "路透報導，中國正考慮限制海外使用其最先進AI模型，並可能將洩露AI技術納入《國安法》規管。此舉恐衝擊全球AI市場，加劇中美科技戰。",
      "region": "int",
      "topic": "ai"
    },
    {
      "title": "SpaceX汰除260顆星鏈衛星",
      "summary": "SpaceX半年內汰除260顆星鏈低軌衛星，受控重返大氣層銷毀，以降低太空垃圾風險。此舉顯示其對軌道環境的重視，但大量衛星燃燒的環境影響仍待研究。",
      "region": "int",
      "topic": "sat"
    },
    {
      "title": "SpaceX申請10萬顆AI衛星",
      "summary": "SpaceX向FCC申請部署10萬顆第三代衛星，旨在打造AI時代的全球通訊底座。該系統將提供極低延遲、高吞吐量服務，承載全球大部分網路流量及AI設備需求。",
      "region": "int",
      "topic": "sat"
    }
  ]
}